ntrfc/__init__.py
ntrfc/ntrfc.py
ntrfc/data/README.md
ntrfc/data/compressor_cascade/README.md
ntrfc/data/compressor_cascade/profilepoints.txt
ntrfc/data/openfoam_cascade_case/README.md
ntrfc/data/openfoam_cascade_case/internal.vtu
ntrfc/data/openfoam_cascade_case/boundary/blade_wall.vtp
ntrfc/data/openfoam_cascade_case/boundary/inlet.vtp
ntrfc/data/openfoam_cascade_case/boundary/outlet.vtp
ntrfc/data/openfoam_probedata/postProcessing/probes/0/T
ntrfc/data/openfoam_probedata/postProcessing/probes/0/U
ntrfc/data/openfoam_probedata/postProcessing/probes/0/p
ntrfc/data/openfoam_probedata/postProcessing/probes/0/rho
ntrfc/data/openfoam_probedata/postProcessing/probes/0.00943924517741/T
ntrfc/data/openfoam_probedata/postProcessing/probes/0.00943924517741/U
ntrfc/data/openfoam_probedata/postProcessing/probes/0.00943924517741/p
ntrfc/data/openfoam_probedata/postProcessing/probes/0.00943924517741/rho
ntrfc/data/t106_cascadecase_how5/Readme.md
ntrfc/data/t106_cascadecase_how5/profilepoints.txt
ntrfc/data/turbine_cascade/README.md
ntrfc/data/turbine_cascade/profilepoints.txt
ntrfc/filehandling/__init__.py
ntrfc/filehandling/datafiles.py
ntrfc/filehandling/mesh.py
ntrfc/fluid/__init__.py
ntrfc/fluid/fluid.py
ntrfc/fluid/isentropic.py
ntrfc/fluid/turbulence.py
ntrfc/geometry/__init__.py
ntrfc/geometry/alphashape.py
ntrfc/geometry/line.py
ntrfc/geometry/plane.py
ntrfc/geometry/surface.py
ntrfc/math/__init__.py
ntrfc/math/methods.py
ntrfc/math/vectorcalc.py
ntrfc/meshquality/__init__.py
ntrfc/meshquality/aspect_ratio.py
ntrfc/meshquality/grid_convergece_index.py
ntrfc/meshquality/meshexpansion.py
ntrfc/meshquality/nondimensionals.py
ntrfc/meshquality/skewness.py
ntrfc/meshquality/standards.py
ntrfc/timeseries/__init__.py
ntrfc/timeseries/integral_scales.py
ntrfc/timeseries/stationarity.py
ntrfc/turbo/__init__.py
ntrfc/turbo/bladeloading.py
ntrfc/turbo/cascade_geometry.py
ntrfc/turbo/domaingen_cascade.py
ntrfc/turbo/integrals.py
ntrfc/turbo/pointcloud_methods.py
ntrfc-0.2.5.dist-info/AUTHORS.rst
ntrfc-0.2.5.dist-info/LICENSE
ntrfc-0.2.5.dist-info/METADATA
ntrfc-0.2.5.dist-info/WHEEL
ntrfc-0.2.5.dist-info/entry_points.txt
ntrfc-0.2.5.dist-info/top_level.txt
ntrfc-0.2.5.dist-info/RECORD
