Metadata-Version: 2.2
Name: ntrfc
Version: 0.2.5
Summary: Numerical Test Rig for Cascades. A workflows-library for CFD analysis of cascade-flows
Author-email: Malte Nyhuis <nyhuis@tfd.uni-hannover.de>
License: MIT License
Keywords: ntrfc
Classifier: Development Status :: 3 - Alpha
Classifier: Intended Audience :: Developers
Classifier: License :: OSI Approved :: MIT License
Classifier: Natural Language :: English
Classifier: Programming Language :: Python :: 3.11
Requires-Python: >=3.10
License-File: LICENSE
License-File: AUTHORS.rst
Requires-Dist: pip>=23
Requires-Dist: open3d==0.19.0
Requires-Dist: numpy==1.26.4
Requires-Dist: matplotlib==3.10.1
Requires-Dist: pytest==8.3.5
Requires-Dist: trame==3.8.1
Requires-Dist: pyvista[all]==0.44.2
Requires-Dist: PyYAML==6.0.2
Requires-Dist: scipy==1.15.2
Requires-Dist: pandas==2.2.3
Requires-Dist: fluidfoam==0.2.9
Requires-Dist: tqdm==4.67.1
Requires-Dist: statsmodels>=0.14.4
Requires-Dist: imageio==2.37.0
Requires-Dist: jupyter
Requires-Dist: sphinx
Requires-Dist: gmsh==4.13.1
Requires-Dist: shapely==2.0.7
Requires-Dist: scikit-image==0.25.2
Provides-Extra: test
Requires-Dist: pytest>=3; extra == "test"
